[{"prim":"switch","nodes":{"cond":"99","follow":"118"},"entry":"99"},{"prim":"switch","nodes":{"cond":"268","follow":"373"},"entry":"268"},{"prim":"switch","nodes":{"cond":"261","follow":"268"},"entry":"261"},{"prim":"switch","nodes":{"cond":"134","follow":"142"},"entry":"134"},{"prim":"switch","nodes":{"body_0":"81","cond":"73","follow":"390"},"entry":"73"},{"prim":"pre_loop","nodes":{"body_0":"134","body_1":"145","body_2":"141","body_3":"139","body_4":"140","body_5":"142","latch":"142"},"entry":"134"},{"prim":"pre_loop","nodes":{"body_0":"99","body_1":"106","body_2":"102","body_3":"118","latch":"118"},"entry":"99"},{"prim":"post_loop","nodes":{"body_0":"168","latch":"168"},"entry":"168"},{"prim":"post_loop","nodes":{"body_0":"222","latch":"222"},"entry":"222"},{"prim":"pre_loop","nodes":{"body_0":"238","body_1":"243","body_2":"241","latch":"241"},"entry":"238"},{"prim":"post_loop","nodes":{"body_0":"73","body_1":"378","body_2":"374","body_3":"81","body_4":"390","latch":"390"},"entry":"73"},{"prim":"post_loop","nodes":{"body_0":"68","body_1":"73","body_2":"399","latch":"399"},"entry":"68"},{"prim":"if","nodes":{"cond":"407","follow":"412"},"entry":"407"},{"prim":"if","nodes":{"body_0":"325","body_1":"329","body_2":"343","body_3":"345","body_4":"350","body_5":"124","body_6":"95","body_7":"106","body_8":"84","cond":"323","follow":"343"},"entry":"323"},{"prim":"if","nodes":{"body_0":"293","body_1":"297","body_2":"311","body_3":"313","body_4":"318","cond":"291","follow":"311"},"entry":"291"},{"prim":"if","nodes":{"body_0":"362","body_1":"363","body_2":"368","body_3":"279","body_4":"281","body_5":"286","body_6":"355","cond":"255","follow":"261"},"entry":"255"},{"prim":"if","nodes":{"body_0":"210","body_1":"243","cond":"206","follow":"218"},"entry":"206"},{"prim":"if","nodes":{"body_0":"191","body_1":"195","body_2":"202","cond":"182","follow":"231"},"entry":"182"},{"prim":"if","nodes":{"body_0":"155","cond":"151","follow":"177"},"entry":"151"},{"prim":"if","nodes":{"cond":"147","follow":"168"},"entry":"147"},{"prim":"if","nodes":{"cond":"145","follow":"182"},"entry":"145"},{"prim":"if","nodes":{"body_0":"37","body_1":"378","cond":"32","follow":"45"},"entry":"32"},{"prim":"if","nodes":{"body_0":"27","body_1":"15","body_2":"21","cond":"2","follow":"415"},"entry":"2"}]
