[{"prim":"pre_loop","nodes":{"body_0":"29","body_1":"47","latch":"47"},"entry":"29"},{"prim":"post_loop","nodes":{"body_0":"131","body_1":"140","body_2":"144","body_3":"168","body_4":"189","latch":"189"},"entry":"131"},{"prim":"post_loop","nodes":{"body_0":"225","latch":"225"},"entry":"225"},{"prim":"post_loop","nodes":{"body_0":"23","body_1":"29","body_2":"64","latch":"101"},"entry":"23"},{"prim":"pre_loop","nodes":{"body_0":"201","body_1":"217","body_2":"206","body_3":"223","latch":"236"},"entry":"201"},{"prim":"if","nodes":{"body_0":"173","body_1":"217","body_2":"206","body_3":"209","cond":"168","follow":"184"},"entry":"168"},{"prim":"if","nodes":{"body_0":"157","body_1":"160","body_2":"164","cond":"150","follow":"157"},"entry":"150"},{"prim":"if","nodes":{"body_0":"147","cond":"144","follow":"150"},"entry":"144"},{"prim":"if","nodes":{"body_0":"140","cond":"117","follow":"194"},"entry":"117"},{"prim":"if","nodes":{"body_0":"74","cond":"64","follow":"101"},"entry":"64"},{"prim":"if","nodes":{"cond":"4","follow":"117"},"entry":"4"}]
