[{"prim":"post_loop","nodes":{"body_0":"34","body_1":"40","body_2":"45","latch":"45"},"entry":"34"},{"prim":"pre_loop","nodes":{"body_0":"53","body_1":"58","latch":"58"},"entry":"53"},{"prim":"pre_loop","nodes":{"body_0":"123","body_1":"128","body_2":"132","latch":"132"},"entry":"123"},{"prim":"post_loop","nodes":{"body_0":"291","latch":"291"},"entry":"291"},{"prim":"post_loop","nodes":{"body_0":"258","latch":"258"},"entry":"258"},{"prim":"post_loop","nodes":{"body_0":"161","latch":"161"},"entry":"161"},{"prim":"pre_loop","nodes":{"body_0":"88","body_1":"123","body_2":"94","body_3":"135","body_4":"139","latch":"221"},"entry":"88"},{"prim":"inf_loop","nodes":{"body_0":"82","body_1":"88","latch":"309"},"entry":"82"},{"prim":"if","nodes":{"cond":"152","follow":"161"},"entry":"152"},{"prim":"if","nodes":{"cond":"149","follow":"169"},"entry":"149"},{"prim":"if","nodes":{"cond":"145","follow":"175"},"entry":"145"},{"prim":"if","nodes":{"body_0":"212","cond":"203","follow":"212"},"entry":"203"},{"prim":"if","nodes":{"cond":"197","follow":"203"},"entry":"197"},{"prim":"if","nodes":{"body_0":"180","cond":"177","follow":"197"},"entry":"177"},{"prim":"if","nodes":{"body_0":"139","cond":"249","follow":"258"},"entry":"249"},{"prim":"if","nodes":{"cond":"246","follow":"266"},"entry":"246"},{"prim":"if","nodes":{"body_0":"232","body_1":"239","cond":"282","follow":"291"},"entry":"282"},{"prim":"if","nodes":{"cond":"279","follow":"299"},"entry":"279"},{"prim":"if","nodes":{"body_0":"272","cond":"230","follow":"309"},"entry":"230"},{"prim":"if","nodes":{"body_0":"129","body_1":"94","body_2":"104","body_3":"135","cond":"128","follow":"133"},"entry":"128"},{"prim":"if","nodes":{"body_0":"62","cond":"29","follow":"319"},"entry":"29"},{"prim":"if","nodes":{"cond":"21","follow":"29"},"entry":"21"},{"prim":"if","nodes":{"body_0":"12","cond":"3","follow":"21"},"entry":"3"}]
