[{"prim":"if_return","nodes":{"body":"72","cond":"69","exit":"73"},"entry":"69","exit":"73"},{"prim":"if_return","nodes":{"body":"45","cond":"43","exit":"46"},"entry":"43","exit":"46"},{"prim":"if_return","nodes":{"body":"13","cond":"6","exit":"14"},"entry":"6","exit":"14"},{"prim":"if_return","nodes":{"body":"42","cond":"37","exit":"39"},"entry":"37","exit":"39"},{"prim":"if_else","nodes":{"body_false":"84","body_true":"86","cond":"79","exit":"87"},"entry":"79","exit":"87"},{"prim":"if_return","nodes":{"body":"79","cond":"61","exit":"69"},"entry":"61","exit":"69"}]
