[{"prim":"seq","nodes":{"entry":"74","exit":"75"},"entry":"74","exit":"75"},{"prim":"if_else","nodes":{"body_false":"68","body_true":"52","cond":"44","exit":"74"},"entry":"44","exit":"74"},{"prim":"pre_loop","nodes":{"body":"44","cond":"40","exit":"78"},"entry":"40","exit":"78"},{"prim":"seq","nodes":{"entry":"39","exit":"40"},"entry":"39","exit":"40"},{"prim":"if","nodes":{"body":"39","cond":"28","exit":"83"},"entry":"28","exit":"83"},{"prim":"if_else","nodes":{"body_false":"27","body_true":"22","cond":"2","exit":"28"},"entry":"2","exit":"28"}]
