[{"prim":"seq","nodes":{"entry":"45","exit":"46"},"entry":"45","exit":"46"},{"prim":"if","nodes":{"body":"35","cond":"29","exit":"41"},"entry":"29","exit":"41"},{"prim":"if","nodes":{"body":"29","cond":"26","exit":"43"},"entry":"26","exit":"43"},{"prim":"pre_loop","nodes":{"body":"45","cond":"26","exit":"50"},"entry":"26","exit":"50"},{"prim":"seq","nodes":{"entry":"21","exit":"26"},"entry":"21","exit":"26"},{"prim":"if","nodes":{"body":"53","cond":"21","exit":"59"},"entry":"21","exit":"59"},{"prim":"if_else","nodes":{"body_false":"19","body_true":"15","cond":"4","exit":"21"},"entry":"4","exit":"21"}]
