[{"prim":"pre_loop","nodes":{"body_0":"14","body_1":"21","body_2":"46","latch":"43"},"entry":"14"},{"prim":"pre_loop","nodes":{"body_0":"84","body_1":"119","body_2":"91","latch":"116"},"entry":"84"},{"prim":"if","nodes":{"cond":"91","follow":"115"},"entry":"91"},{"prim":"if","nodes":{"cond":"119","follow":"128"},"entry":"119"},{"prim":"if","nodes":{"cond":"72","follow":"83"},"entry":"72"},{"prim":"if","nodes":{"body_0":"56","body_1":"61","cond":"46","follow":"72"},"entry":"46"},{"prim":"if","nodes":{"body_0":"33","cond":"21","follow":"42"},"entry":"21"}]
