[{"prim":"pre_loop","nodes":{"body_0":"39","body_1":"54","body_2":"51","latch":"51"},"entry":"39"},{"prim":"pre_loop","nodes":{"body_0":"75","body_1":"90","body_2":"87","latch":"87"},"entry":"75"},{"prim":"pre_loop","nodes":{"body_0":"135","body_1":"150","body_2":"147","latch":"147"},"entry":"135"},{"prim":"if","nodes":{"cond":"150","follow":"155"},"entry":"150"},{"prim":"if","nodes":{"body_0":"113","body_1":"121","cond":"106","follow":"121"},"entry":"106"},{"prim":"if","nodes":{"body_0":"101","cond":"96","follow":"156"},"entry":"96"},{"prim":"if","nodes":{"cond":"90","follow":"95"},"entry":"90"},{"prim":"if","nodes":{"body_0":"59","cond":"54","follow":"96"},"entry":"54"},{"prim":"if","nodes":{"cond":"31","follow":"38"},"entry":"31"},{"prim":"if","nodes":{"cond":"18","follow":"162"},"entry":"18"},{"prim":"if","nodes":{"body_0":"10","cond":"2","follow":"18"},"entry":"2"}]
