[{"prim":"if","nodes":{"body_0":"115","cond":"107","follow":"126"},"entry":"107"},{"prim":"if","nodes":{"cond":"95","follow":"106"},"entry":"95"},{"prim":"if","nodes":{"cond":"77","follow":"107"},"entry":"77"},{"prim":"if","nodes":{"cond":"72","follow":"127"},"entry":"72"},{"prim":"if","nodes":{"cond":"57","follow":"70"},"entry":"57"},{"prim":"if","nodes":{"cond":"44","follow":"71"},"entry":"44"},{"prim":"if","nodes":{"cond":"25","follow":"44"},"entry":"25"},{"prim":"if","nodes":{"cond":"13","follow":"25"},"entry":"13"},{"prim":"if","nodes":{"cond":"2","follow":"72"},"entry":"2"}]
