[{"prim":"pre_loop","nodes":{"body_0":"17","body_1":"23","body_2":"28","latch":"70"},"entry":"17"},{"prim":"pre_loop","nodes":{"body_0":"123","body_1":"134","latch":"142"},"entry":"123"},{"prim":"pre_loop","nodes":{"body_0":"190","body_1":"215","body_2":"194","latch":"212"},"entry":"190"},{"prim":"if","nodes":{"body_0":"49","cond":"30","follow":"70"},"entry":"30"},{"prim":"if","nodes":{"cond":"194","follow":"211"},"entry":"194"},{"prim":"if","nodes":{"body_0":"152","body_1":"158","cond":"134","follow":"141"},"entry":"134"},{"prim":"if","nodes":{"body_0":"114","cond":"99","follow":"220"},"entry":"99"},{"prim":"if","nodes":{"body_0":"28","body_1":"78","cond":"2","follow":"232"},"entry":"2"}]
