[{"prim":"if","nodes":{"body":"226","cond":"221","exit":"249"},"entry":"221","exit":"249"},{"prim":"if","nodes":{"body":"184","cond":"179","exit":"193"},"entry":"179","exit":"193"},{"prim":"if","nodes":{"body":"179","cond":"175","exit":"195"},"entry":"175","exit":"195"},{"prim":"pre_loop","nodes":{"body":"197","cond":"175","exit":"200"},"entry":"175","exit":"200"},{"prim":"seq","nodes":{"entry":"164","exit":"175"},"entry":"164","exit":"175"},{"prim":"if","nodes":{"body":"164","cond":"152","exit":"221"},"entry":"152","exit":"221"}]
