[{"prim":"seq","nodes":{"entry":"3760","exit":"3761"},"entry":"3760","exit":"3761"},{"prim":"seq","nodes":{"entry":"8007","exit":"8022"},"entry":"8007","exit":"8022"},{"prim":"seq","nodes":{"entry":"8068","exit":"8078"},"entry":"8068","exit":"8078"},{"prim":"seq","nodes":{"entry":"4745","exit":"4746"},"entry":"4745","exit":"4746"},{"prim":"seq","nodes":{"entry":"8826","exit":"8827"},"entry":"8826","exit":"8827"},{"prim":"seq","nodes":{"entry":"7644","exit":"7651"},"entry":"7644","exit":"7651"},{"prim":"seq","nodes":{"entry":"3225","exit":"3228"},"entry":"3225","exit":"3228"},{"prim":"seq","nodes":{"entry":"8590","exit":"8604"},"entry":"8590","exit":"8604"},{"prim":"seq","nodes":{"entry":"6804","exit":"6805"},"entry":"6804","exit":"6805"},{"prim":"seq","nodes":{"entry":"8808","exit":"8809"},"entry":"8808","exit":"8809"},{"prim":"seq","nodes":{"entry":"6628","exit":"6640"},"entry":"6628","exit":"6640"},{"prim":"seq","nodes":{"entry":"3489","exit":"3492"},"entry":"3489","exit":"3492"},{"prim":"seq","nodes":{"entry":"6310","exit":"6311"},"entry":"6310","exit":"6311"},{"prim":"seq","nodes":{"entry":"7760","exit":"7761"},"entry":"7760","exit":"7761"},{"prim":"seq","nodes":{"entry":"3148","exit":"3155"},"entry":"3148","exit":"3155"},{"prim":"seq","nodes":{"entry":"1126","exit":"1132"},"entry":"1126","exit":"1132"},{"prim":"seq","nodes":{"entry":"976","exit":"981"},"entry":"976","exit":"981"},{"prim":"seq","nodes":{"entry":"4723","exit":"4725"},"entry":"4723","exit":"4725"},{"prim":"seq","nodes":{"entry":"2702","exit":"2707"},"entry":"2702","exit":"2707"},{"prim":"seq","nodes":{"entry":"2851","exit":"2860"},"entry":"2851","exit":"2860"},{"prim":"seq","nodes":{"entry":"3600","exit":"3601"},"entry":"3600","exit":"3601"},{"prim":"seq","nodes":{"entry":"5024","exit":"5027"},"entry":"5024","exit":"5027"},{"prim":"seq","nodes":{"entry":"5189","exit":"5195"},"entry":"5189","exit":"5195"},{"prim":"seq","nodes":{"entry":"3628","exit":"3629"},"entry":"3628","exit":"3629"},{"prim":"seq","nodes":{"entry":"3100","exit":"3108"},"entry":"3100","exit":"3108"},{"prim":"seq","nodes":{"entry":"3148","exit":"3160"},"entry":"3148","exit":"3160"},{"prim":"seq","nodes":{"entry":"5718","exit":"5719"},"entry":"5718","exit":"5719"},{"prim":"seq","nodes":{"entry":"6702","exit":"6710"},"entry":"6702","exit":"6710"},{"prim":"seq","nodes":{"entry":"5123","exit":"5124"},"entry":"5123","exit":"5124"},{"prim":"seq","nodes":{"entry":"2198","exit":"2199"},"entry":"2198","exit":"2199"},{"prim":"seq","nodes":{"entry":"3100","exit":"3113"},"entry":"3100","exit":"3113"},{"prim":"seq","nodes":{"entry":"3146","exit":"3148"},"entry":"3146","exit":"3148"},{"prim":"seq","nodes":{"entry":"8359","exit":"8367"},"entry":"8359","exit":"8367"},{"prim":"seq","nodes":{"entry":"6959","exit":"6965"},"entry":"6959","exit":"6965"},{"prim":"seq","nodes":{"entry":"7184","exit":"7185"},"entry":"7184","exit":"7185"},{"prim":"seq","nodes":{"entry":"2799","exit":"2814"},"entry":"2799","exit":"2814"},{"prim":"seq","nodes":{"entry":"3089","exit":"3100"},"entry":"3089","exit":"3100"},{"prim":"seq","nodes":{"entry":"4697","exit":"4699"},"entry":"4697","exit":"4699"},{"prim":"seq","nodes":{"entry":"3315","exit":"3330"},"entry":"3315","exit":"3330"},{"prim":"seq","nodes":{"entry":"1541","exit":"1542"},"entry":"1541","exit":"1542"},{"prim":"seq","nodes":{"entry":"2594","exit":"2615"},"entry":"2594","exit":"2615"},{"prim":"seq","nodes":{"entry":"7449","exit":"7463"},"entry":"7449","exit":"7463"},{"prim":"seq","nodes":{"entry":"1020","exit":"1026"},"entry":"1020","exit":"1026"},{"prim":"seq","nodes":{"entry":"4887","exit":"4888"},"entry":"4887","exit":"4888"},{"prim":"seq","nodes":{"entry":"3755","exit":"3760"},"entry":"3755","exit":"3760"},{"prim":"seq","nodes":{"entry":"1843","exit":"1877"},"entry":"1843","exit":"1877"},{"prim":"pre_loop","nodes":{"body":"7184","cond":"7179","exit":"7189"},"entry":"7179","exit":"7189"},{"prim":"seq","nodes":{"entry":"7175","exit":"7179"},"entry":"7175","exit":"7179"},{"prim":"pre_loop","nodes":{"body":"8068","cond":"8064","exit":"8081"},"entry":"8064","exit":"8081"},{"prim":"seq","nodes":{"entry":"8023","exit":"8064"},"entry":"8023","exit":"8064"},{"prim":"pre_loop","nodes":{"body":"3650","cond":"3644","exit":"3666"},"entry":"3644","exit":"3666"},{"prim":"seq","nodes":{"entry":"3643","exit":"3644"},"entry":"3643","exit":"3644"},{"prim":"pre_loop","nodes":{"body":"7449","cond":"7446","exit":"7466"},"entry":"7446","exit":"7466"},{"prim":"seq","nodes":{"entry":"7437","exit":"7446"},"entry":"7437","exit":"7446"},{"prim":"pre_loop","nodes":{"body":"5123","cond":"5118","exit":"5128"},"entry":"5118","exit":"5128"},{"prim":"seq","nodes":{"entry":"5114","exit":"5118"},"entry":"5114","exit":"5118"},{"prim":"pre_loop","nodes":{"body":"877","cond":"874","exit":"888"},"entry":"874","exit":"888"},{"prim":"seq","nodes":{"entry":"852","exit":"874"},"entry":"852","exit":"874"},{"prim":"pre_loop","nodes":{"body":"8359","cond":"8355","exit":"8370"},"entry":"8355","exit":"8370"},{"prim":"seq","nodes":{"entry":"8342","exit":"8355"},"entry":"8342","exit":"8355"},{"prim":"pre_loop","nodes":{"body":"6959","cond":"6955","exit":"6968"},"entry":"6955","exit":"6968"},{"prim":"seq","nodes":{"entry":"6874","exit":"6955"},"entry":"6874","exit":"6955"},{"prim":"pre_loop","nodes":{"body":"7644","cond":"7641","exit":"7656"},"entry":"7641","exit":"7656"},{"prim":"seq","nodes":{"entry":"7634","exit":"7641"},"entry":"7634","exit":"7641"},{"prim":"pre_loop","nodes":{"body":"8590","cond":"8587","exit":"8607"},"entry":"8587","exit":"8607"},{"prim":"seq","nodes":{"entry":"8578","exit":"8587"},"entry":"8578","exit":"8587"},{"prim":"if","nodes":{"body":"4596","cond":"4592","exit":"4599"},"entry":"4592","exit":"4599"},{"prim":"if","nodes":{"body":"8294","cond":"8281","exit":"8299"},"entry":"8281","exit":"8299"},{"prim":"if","nodes":{"body":"7225","cond":"7205","exit":"7233"},"entry":"7205","exit":"7233"},{"prim":"if","nodes":{"body":"7746","cond":"7743","exit":"7749"},"entry":"7743","exit":"7749"},{"prim":"if","nodes":{"body":"8800","cond":"8789","exit":"8808"},"entry":"8789","exit":"8808"},{"prim":"pre_loop","nodes":{"body":"8789","cond":"8783","exit":"8812"},"entry":"8783","exit":"8812"},{"prim":"seq","nodes":{"entry":"8782","exit":"8783"},"entry":"8782","exit":"8783"},{"prim":"if","nodes":{"body":"6796","cond":"6793","exit":"6802"},"entry":"6793","exit":"6802"},{"prim":"pre_loop","nodes":{"body":"6804","cond":"6793","exit":"6809"},"entry":"6793","exit":"6809"},{"prim":"seq","nodes":{"entry":"6786","exit":"6793"},"entry":"6786","exit":"6793"},{"prim":"if","nodes":{"body":"3680","cond":"3669","exit":"3685"},"entry":"3669","exit":"3685"},{"prim":"if","nodes":{"body":"5303","cond":"5296","exit":"5308"},"entry":"5296","exit":"5308"},{"prim":"if","nodes":{"body":"7680","cond":"7657","exit":"7682"},"entry":"7657","exit":"7682"},{"prim":"if","nodes":{"body":"5315","cond":"5296","exit":"5320"},"entry":"5296","exit":"5320"},{"prim":"if","nodes":{"body":"6844","cond":"6832","exit":"6847"},"entry":"6832","exit":"6847"},{"prim":"if","nodes":{"body":"7765","cond":"7762","exit":"7767"},"entry":"7762","exit":"7767"},{"prim":"if","nodes":{"body":"5743","cond":"5724","exit":"5748"},"entry":"5724","exit":"5748"},{"prim":"if","nodes":{"body":"1762","cond":"1749","exit":"1765"},"entry":"1749","exit":"1765"},{"prim":"if","nodes":{"body":"3247","cond":"3235","exit":"3250"},"entry":"3235","exit":"3250"},{"prim":"if","nodes":{"body":"4580","cond":"4576","exit":"4583"},"entry":"4576","exit":"4583"},{"prim":"if","nodes":{"body":"8836","cond":"8831","exit":"8837"},"entry":"8831","exit":"8837"},{"prim":"if","nodes":{"body":"4203","cond":"4197","exit":"4208"},"entry":"4197","exit":"4208"},{"prim":"if","nodes":{"body":"7887","cond":"7883","exit":"7894"},"entry":"7883","exit":"7894"},{"prim":"if","nodes":{"body":"4623","cond":"4616","exit":"4624"},"entry":"4616","exit":"4624"},{"prim":"if","nodes":{"body":"4073","cond":"4068","exit":"4079"},"entry":"4068","exit":"4079"},{"prim":"if","nodes":{"body":"4170","cond":"4163","exit":"4182"},"entry":"4163","exit":"4182"},{"prim":"if","nodes":{"body":"590","cond":"567","exit":"600"},"entry":"567","exit":"600"},{"prim":"if","nodes":{"body":"4592","cond":"4584","exit":"4600"},"entry":"4584","exit":"4600"},{"prim":"if","nodes":{"body":"8184","cond":"8167","exit":"8190"},"entry":"8167","exit":"8190"},{"prim":"if","nodes":{"body":"2818","cond":"2799","exit":"2822"},"entry":"2799","exit":"2822"},{"prim":"if","nodes":{"body":"7323","cond":"7317","exit":"7329"},"entry":"7317","exit":"7329"},{"prim":"if","nodes":{"body":"1911","cond":"1906","exit":"1913"},"entry":"1906","exit":"1913"},{"prim":"if","nodes":{"body":"7931","cond":"7917","exit":"7940"},"entry":"7917","exit":"7940"},{"prim":"if","nodes":{"body":"3480","cond":"3477","exit":"3487"},"entry":"3477","exit":"3487"},{"prim":"pre_loop","nodes":{"body":"3489","cond":"3477","exit":"3496"},"entry":"3477","exit":"3496"},{"prim":"seq","nodes":{"entry":"3473","exit":"3477"},"entry":"3473","exit":"3477"},{"prim":"if","nodes":{"body":"5878","cond":"5867","exit":"5880"},"entry":"5867","exit":"5880"},{"prim":"if","nodes":{"body":"6349","cond":"6339","exit":"6362"},"entry":"6339","exit":"6362"},{"prim":"if","nodes":{"body":"5979","cond":"5957","exit":"5984"},"entry":"5957","exit":"5984"},{"prim":"if","nodes":{"body":"3344","cond":"3335","exit":"3356"},"entry":"3335","exit":"3356"},{"prim":"if","nodes":{"body":"7343","cond":"7331","exit":"7349"},"entry":"7331","exit":"7349"},{"prim":"if","nodes":{"body":"1438","cond":"1435","exit":"1439"},"entry":"1435","exit":"1439"},{"prim":"if","nodes":{"body":"8578","cond":"8562","exit":"8608"},"entry":"8562","exit":"8608"},{"prim":"if","nodes":{"body":"4379","cond":"4367","exit":"4390"},"entry":"4367","exit":"4390"},{"prim":"if","nodes":{"body":"3517","cond":"3512","exit":"3523"},"entry":"3512","exit":"3523"},{"prim":"if","nodes":{"body":"1551","cond":"1546","exit":"1558"},"entry":"1546","exit":"1558"},{"prim":"if","nodes":{"body":"1294","cond":"1281","exit":"1305"},"entry":"1281","exit":"1305"},{"prim":"if","nodes":{"body":"2194","cond":"2191","exit":"2197"},"entry":"2191","exit":"2197"},{"prim":"if","nodes":{"body":"4549","cond":"4536","exit":"4551"},"entry":"4536","exit":"4551"},{"prim":"if","nodes":{"body":"7437","cond":"7421","exit":"7467"},"entry":"7421","exit":"7467"},{"prim":"if","nodes":{"body":"1664","cond":"1658","exit":"1670"},"entry":"1658","exit":"1670"},{"prim":"if","nodes":{"body":"1148","cond":"1141","exit":"1158"},"entry":"1141","exit":"1158"},{"prim":"if","nodes":{"body":"3146","cond":"3114","exit":"3161"},"entry":"3114","exit":"3161"},{"prim":"if","nodes":{"body":"3978","cond":"3955","exit":"3983"},"entry":"3955","exit":"3983"},{"prim":"if","nodes":{"body":"3635","cond":"3632","exit":"3642"},"entry":"3632","exit":"3642"},{"prim":"if","nodes":{"body":"2858","cond":"2853","exit":"2859"},"entry":"2853","exit":"2859"},{"prim":"if","nodes":{"body":"4351","cond":"4329","exit":"4356"},"entry":"4329","exit":"4356"},{"prim":"if","nodes":{"body":"8640","cond":"8635","exit":"8647"},"entry":"8635","exit":"8647"},{"prim":"if","nodes":{"body":"4742","cond":"4739","exit":"4745"},"entry":"4739","exit":"4745"},{"prim":"if","nodes":{"body":"650","cond":"635","exit":"662"},"entry":"635","exit":"662"},{"prim":"if","nodes":{"body":"1639","cond":"1636","exit":"1643"},"entry":"1636","exit":"1643"},{"prim":"if","nodes":{"body":"5169","cond":"5161","exit":"5175"},"entry":"5161","exit":"5175"},{"prim":"if","nodes":{"body":"2878","cond":"2861","exit":"2879"},"entry":"2861","exit":"2879"},{"prim":"if","nodes":{"body":"1901","cond":"1896","exit":"1906"},"entry":"1896","exit":"1906"},{"prim":"if","nodes":{"body":"7686","cond":"7657","exit":"7688"},"entry":"7657","exit":"7688"},{"prim":"if","nodes":{"body":"4901","cond":"4892","exit":"4905"},"entry":"4892","exit":"4905"},{"prim":"if","nodes":{"body":"8494","cond":"8486","exit":"8498"},"entry":"8486","exit":"8498"},{"prim":"if","nodes":{"body":"1896","cond":"1888","exit":"1914"},"entry":"1888","exit":"1914"},{"prim":"if","nodes":{"body":"6300","cond":"6297","exit":"6310"},"entry":"6297","exit":"6310"},{"prim":"if","nodes":{"body":"847","cond":"831","exit":"850"},"entry":"831","exit":"850"},{"prim":"if","nodes":{"body":"2918","cond":"2911","exit":"2920"},"entry":"2911","exit":"2920"},{"prim":"if","nodes":{"body":"8486","cond":"8468","exit":"8499"},"entry":"8468","exit":"8499"},{"prim":"if","nodes":{"body":"3907","cond":"3898","exit":"3913"},"entry":"3898","exit":"3913"},{"prim":"if","nodes":{"body":"6761","cond":"6758","exit":"6770"},"entry":"6758","exit":"6770"},{"prim":"if","nodes":{"body":"6523","cond":"6512","exit":"6526"},"entry":"6512","exit":"6526"},{"prim":"if","nodes":{"body":"7753","cond":"7750","exit":"7760"},"entry":"7750","exit":"7760"},{"prim":"if","nodes":{"body":"776","cond":"762","exit":"782"},"entry":"762","exit":"782"},{"prim":"if","nodes":{"body":"2381","cond":"2361","exit":"2390"},"entry":"2361","exit":"2390"},{"prim":"if","nodes":{"body":"7514","cond":"7509","exit":"7523"},"entry":"7509","exit":"7523"},{"prim":"if","nodes":{"body":"7738","cond":"7732","exit":"7742"},"entry":"7732","exit":"7742"},{"prim":"if","nodes":{"body":"4153","cond":"4135","exit":"4161"},"entry":"4135","exit":"4161"},{"prim":"if","nodes":{"body":"4058","cond":"4053","exit":"4067"},"entry":"4053","exit":"4067"},{"prim":"if","nodes":{"body":"5379","cond":"5376","exit":"5400"},"entry":"5376","exit":"5400"},{"prim":"if","nodes":{"body":"7907","cond":"7897","exit":"7912"},"entry":"7897","exit":"7912"},{"prim":"if","nodes":{"body":"3884","cond":"3879","exit":"3898"},"entry":"3879","exit":"3898"},{"prim":"if","nodes":{"body":"6339","cond":"6332","exit":"6363"},"entry":"6332","exit":"6363"},{"prim":"if","nodes":{"body":"8873","cond":"8849","exit":"8875"},"entry":"8849","exit":"8875"},{"prim":"if","nodes":{"body":"831","cond":"807","exit":"851"},"entry":"807","exit":"851"},{"prim":"if","nodes":{"body":"8879","cond":"8849","exit":"8884"},"entry":"8849","exit":"8884"},{"prim":"if","nodes":{"body":"1504","cond":"1501","exit":"1505"},"entry":"1501","exit":"1505"},{"prim":"if","nodes":{"body":"7535","cond":"7528","exit":"7540"},"entry":"7528","exit":"7540"},{"prim":"if","nodes":{"body":"7528","cond":"7509","exit":"7543"},"entry":"7509","exit":"7543"},{"prim":"if_else","nodes":{"body_false":"6052","body_true":"6048","cond":"6010","exit":"6053"},"entry":"6010","exit":"6053"},{"prim":"if_else","nodes":{"body_false":"7476","body_true":"7490","cond":"7421","exit":"7504"},"entry":"7421","exit":"7504"},{"prim":"if_else","nodes":{"body_false":"3447","body_true":"3442","cond":"3425","exit":"3452"},"entry":"3425","exit":"3452"},{"prim":"if","nodes":{"body":"3425","cond":"3415","exit":"3471"},"entry":"3415","exit":"3471"},{"prim":"if_else","nodes":{"body_false":"2157","body_true":"2151","cond":"2148","exit":"2159"},"entry":"2148","exit":"2159"},{"prim":"if_else","nodes":{"body_false":"5099","body_true":"5093","cond":"5085","exit":"5102"},"entry":"5085","exit":"5102"},{"prim":"if_else","nodes":{"body_false":"5867","body_true":"5864","cond":"5849","exit":"5885"},"entry":"5849","exit":"5885"},{"prim":"if_else","nodes":{"body_false":"8427","body_true":"8426","cond":"8420","exit":"8432"},"entry":"8420","exit":"8432"},{"prim":"if_else","nodes":{"body_false":"2653","body_true":"2661","cond":"2641","exit":"2669"},"entry":"2641","exit":"2669"},{"prim":"if_else","nodes":{"body_false":"7285","body_true":"7290","cond":"7279","exit":"7291"},"entry":"7279","exit":"7291"},{"prim":"if_else","nodes":{"body_false":"8756","body_true":"8740","cond":"8735","exit":"8767"},"entry":"8735","exit":"8767"},{"prim":"if_else","nodes":{"body_false":"8420","body_true":"8419","cond":"8413","exit":"8437"},"entry":"8413","exit":"8437"},{"prim":"if_else","nodes":{"body_false":"5085","body_true":"5084","cond":"5081","exit":"5103"},"entry":"5081","exit":"5103"},{"prim":"if_else","nodes":{"body_false":"7743","body_true":"7732","cond":"7729","exit":"7750"},"entry":"7729","exit":"7750"},{"prim":"if_else","nodes":{"body_false":"5348","body_true":"5354","cond":"5340","exit":"5356"},"entry":"5340","exit":"5356"},{"prim":"if_else","nodes":{"body_false":"2292","body_true":"2282","cond":"2273","exit":"2307"},"entry":"2273","exit":"2307"},{"prim":"if_else","nodes":{"body_false":"2900","body_true":"2894","cond":"2888","exit":"2902"},"entry":"2888","exit":"2902"},{"prim":"if_else","nodes":{"body_false":"354","body_true":"340","cond":"335","exit":"355"},"entry":"335","exit":"355"},{"prim":"if_else","nodes":{"body_false":"2123","body_true":"2122","cond":"2115","exit":"2130"},"entry":"2115","exit":"2130"},{"prim":"if_else","nodes":{"body_false":"3235","body_true":"3232","cond":"3229","exit":"3251"},"entry":"3229","exit":"3251"},{"prim":"if_else","nodes":{"body_false":"1782","body_true":"1779","cond":"1766","exit":"1783"},"entry":"1766","exit":"1783"},{"prim":"if_else","nodes":{"body_false":"5137","body_true":"5114","cond":"5109","exit":"5144"},"entry":"5109","exit":"5144"},{"prim":"if_else","nodes":{"body_false":"7198","body_true":"7175","cond":"7170","exit":"7205"},"entry":"7170","exit":"7205"},{"prim":"if_else","nodes":{"body_false":"5994","body_true":"5991","cond":"5957","exit":"5995"},"entry":"5957","exit":"5995"},{"prim":"if_else","nodes":{"body_false":"8735","body_true":"8721","cond":"8714","exit":"8768"},"entry":"8714","exit":"8768"},{"prim":"if_else","nodes":{"body_false":"4041","body_true":"4053","cond":"4018","exit":"4068"},"entry":"4018","exit":"4068"},{"prim":"if_else","nodes":{"body_false":"5263","body_true":"5251","cond":"5230","exit":"5269"},"entry":"5230","exit":"5269"},{"prim":"if_else","nodes":{"body_false":"8707","body_true":"8702","cond":"8696","exit":"8711"},"entry":"8696","exit":"8711"},{"prim":"if_else","nodes":{"body_false":"688","body_true":"685","cond":"680","exit":"695"},"entry":"680","exit":"695"},{"prim":"if_else","nodes":{"body_false":"6176","body_true":"6150","cond":"6144","exit":"6184"},"entry":"6144","exit":"6184"},{"prim":"if_else","nodes":{"body_false":"6010","body_true":"6006","cond":"6000","exit":"6058"},"entry":"6000","exit":"6058"},{"prim":"if_else","nodes":{"body_false":"663","body_true":"635","cond":"630","exit":"669"},"entry":"630","exit":"669"},{"prim":"if","nodes":{"body":"630","cond":"611","exit":"680"},"entry":"611","exit":"680"},{"prim":"if_else","nodes":{"body_false":"3300","body_true":"3307","cond":"3294","exit":"3315"},"entry":"3294","exit":"3315"},{"prim":"seq","nodes":{"entry":"3288","exit":"3294"},"entry":"3288","exit":"3294"},{"prim":"seq","nodes":{"entry":"3288","exit":"3335"},"entry":"3288","exit":"3335"},{"prim":"if_else","nodes":{"body_false":"3796","body_true":"3797","cond":"3792","exit":"3802"},"entry":"3792","exit":"3802"},{"prim":"if_else","nodes":{"body_false":"7129","body_true":"7120","cond":"7115","exit":"7138"},"entry":"7115","exit":"7138"},{"prim":"if_else","nodes":{"body_false":"2225","body_true":"2217","cond":"2214","exit":"2233"},"entry":"2214","exit":"2233"},{"prim":"if_else","nodes":{"body_false":"4367","body_true":"4393","cond":"4359","exit":"4404"},"entry":"4359","exit":"4404"},{"prim":"if","nodes":{"body":"4359","cond":"4329","exit":"4405"},"entry":"4329","exit":"4405"},{"prim":"if_else","nodes":{"body_false":"2214","body_true":"2206","cond":"2203","exit":"2234"},"entry":"2203","exit":"2234"},{"prim":"if_else","nodes":{"body_false":"6242","body_true":"6239","cond":"6222","exit":"6245"},"entry":"6222","exit":"6245"},{"prim":"if_else","nodes":{"body_false":"1658","body_true":"1654","cond":"1648","exit":"1671"},"entry":"1648","exit":"1671"},{"prim":"if_else","nodes":{"body_false":"6512","body_true":"6511","cond":"6483","exit":"6532"},"entry":"6483","exit":"6532"},{"prim":"if_else","nodes":{"body_false":"2264","body_true":"2255","cond":"2235","exit":"2273"},"entry":"2235","exit":"2273"},{"prim":"if_else","nodes":{"body_false":"3283","body_true":"3279","cond":"3273","exit":"3288"},"entry":"3273","exit":"3288"},{"prim":"if_else","nodes":{"body_false":"2358","body_true":"2350","cond":"2331","exit":"2360"},"entry":"2331","exit":"2360"},{"prim":"if_else","nodes":{"body_false":"3669","body_true":"3686","cond":"3643","exit":"3697"},"entry":"3643","exit":"3697"},{"prim":"if_else","nodes":{"body_false":"2778","body_true":"2787","cond":"2772","exit":"2799"},"entry":"2772","exit":"2799"},{"prim":"seq","nodes":{"entry":"2749","exit":"2772"},"entry":"2749","exit":"2772"},{"prim":"seq","nodes":{"entry":"2749","exit":"2824"},"entry":"2749","exit":"2824"},{"prim":"if_else","nodes":{"body_false":"4197","body_true":"4188","cond":"4163","exit":"4209"},"entry":"4163","exit":"4209"},{"prim":"if_else","nodes":{"body_false":"4833","body_true":"4830","cond":"4823","exit":"4834"},"entry":"4823","exit":"4834"},{"prim":"if_else","nodes":{"body_false":"2039","body_true":"2029","cond":"2026","exit":"2049"},"entry":"2026","exit":"2049"},{"prim":"if_else","nodes":{"body_false":"6483","body_true":"6456","cond":"6447","exit":"6533"},"entry":"6447","exit":"6533"},{"prim":"if_else","nodes":{"body_false":"2026","body_true":"2016","cond":"2013","exit":"2050"},"entry":"2013","exit":"2050"},{"prim":"if_else","nodes":{"body_false":"4162","body_true":"4135","cond":"4114","exit":"4163"},"entry":"4114","exit":"4163"},{"prim":"if_else","nodes":{"body_false":"6331","body_true":"6330","cond":"6312","exit":"6332"},"entry":"6312","exit":"6332"},{"prim":"if_else","nodes":{"body_false":"1648","body_true":"1636","cond":"1633","exit":"1674"},"entry":"1633","exit":"1674"},{"prim":"if_else","nodes":{"body_false":"7115","body_true":"7106","cond":"7100","exit":"7139"},"entry":"7100","exit":"7139"},{"prim":"if_else","nodes":{"body_false":"5335","body_true":"5339","cond":"5296","exit":"5340"},"entry":"5296","exit":"5340"},{"prim":"if_else","nodes":{"body_false":"3209","body_true":"3210","cond":"3202","exit":"3214"},"entry":"3202","exit":"3214"},{"prim":"if_else","nodes":{"body_false":"3790","body_true":"3789","cond":"3783","exit":"3791"},"entry":"3783","exit":"3791"},{"prim":"if_else","nodes":{"body_false":"1630","body_true":"1627","cond":"1620","exit":"1631"},"entry":"1620","exit":"1631"},{"prim":"if","nodes":{"body":"1620","cond":"1617","exit":"1633"},"entry":"1617","exit":"1633"},{"prim":"if","nodes":{"body":"1617","cond":"1614","exit":"1675"},"entry":"1614","exit":"1675"},{"prim":"if_else","nodes":{"body_false":"8157","body_true":"8150","cond":"8133","exit":"8167"},"entry":"8133","exit":"8167"},{"prim":"if_else","nodes":{"body_false":"6220","body_true":"6218","cond":"6193","exit":"6222"},"entry":"6193","exit":"6222"},{"prim":"if_else","nodes":{"body_false":"7831","body_true":"7836","cond":"7826","exit":"7849"},"entry":"7826","exit":"7849"},{"prim":"if_else","nodes":{"body_false":"7569","body_true":"7588","cond":"7558","exit":"7595"},"entry":"7558","exit":"7595"},{"prim":"if_else","nodes":{"body_false":"1614","body_true":"1610","cond":"1606","exit":"1676"},"entry":"1606","exit":"1676"},{"prim":"if_else","nodes":{"body_false":"1606","body_true":"1602","cond":"1591","exit":"1677"},"entry":"1591","exit":"1677"},{"prim":"if_else","nodes":{"body_false":"4584","body_true":"4576","cond":"4568","exit":"4601"},"entry":"4568","exit":"4601"}]
