[{"prim":"seq","nodes":{"entry":"220","exit":"230"},"entry":"220","exit":"230"},{"prim":"pre_loop","nodes":{"body":"220","cond":"216","exit":"233"},"entry":"216","exit":"233"},{"prim":"seq","nodes":{"entry":"212","exit":"216"},"entry":"212","exit":"216"},{"prim":"if","nodes":{"body":"183","cond":"169","exit":"186"},"entry":"169","exit":"186"},{"prim":"if","nodes":{"body":"44","cond":"38","exit":"49"},"entry":"38","exit":"49"},{"prim":"pre_loop","nodes":{"body":"51","cond":"38","exit":"52"},"entry":"38","exit":"52"},{"prim":"seq","nodes":{"entry":"36","exit":"38"},"entry":"36","exit":"38"},{"prim":"pre_loop","nodes":{"body":"36","cond":"32","exit":"60"},"entry":"32","exit":"60"},{"prim":"seq","nodes":{"entry":"31","exit":"32"},"entry":"31","exit":"32"},{"prim":"if","nodes":{"body":"245","cond":"241","exit":"246"},"entry":"241","exit":"246"},{"prim":"if","nodes":{"body":"169","cond":"162","exit":"187"},"entry":"162","exit":"187"},{"prim":"if","nodes":{"body":"198","cond":"162","exit":"199"},"entry":"162","exit":"199"},{"prim":"if_else","nodes":{"body_false":"212","body_true":"207","cond":"200","exit":"234"},"entry":"200","exit":"234"},{"prim":"if_else","nodes":{"body_false":"200","body_true":"162","cond":"155","exit":"235"},"entry":"155","exit":"235"},{"prim":"if_else","nodes":{"body_false":"102","body_true":"98","cond":"95","exit":"104"},"entry":"95","exit":"104"},{"prim":"if_else","nodes":{"body_false":"150","body_true":"155","cond":"143","exit":"236"},"entry":"143","exit":"236"},{"prim":"if_else","nodes":{"body_false":"105","body_true":"95","cond":"89","exit":"110"},"entry":"89","exit":"110"},{"prim":"if_else","nodes":{"body_false":"143","body_true":"138","cond":"131","exit":"237"},"entry":"131","exit":"237"},{"prim":"if_else","nodes":{"body_false":"131","body_true":"130","cond":"89","exit":"238"},"entry":"89","exit":"238"}]
