[{"prim":"seq","nodes":{"entry":"153","exit":"154"},"entry":"153","exit":"154"},{"prim":"seq","nodes":{"entry":"216","exit":"217"},"entry":"216","exit":"217"},{"prim":"seq","nodes":{"entry":"67","exit":"74"},"entry":"67","exit":"74"},{"prim":"pre_loop","nodes":{"body":"67","cond":"63","exit":"77"},"entry":"63","exit":"77"},{"prim":"seq","nodes":{"entry":"55","exit":"63"},"entry":"55","exit":"63"},{"prim":"if","nodes":{"body":"183","cond":"175","exit":"194"},"entry":"175","exit":"194"},{"prim":"if","nodes":{"body":"54","cond":"42","exit":"55"},"entry":"42","exit":"55"}]
