[{"prim":"pre_loop","nodes":{"body_0":"30","body_1":"33","body_2":"39","latch":"87"},"entry":"30"},{"prim":"post_loop","nodes":{"body_0":"215","body_1":"218","body_2":"233","latch":"256"},"entry":"215"},{"prim":"pre_loop","nodes":{"body_0":"129","body_1":"132","body_2":"138","latch":"155"},"entry":"129"},{"prim":"pre_loop","nodes":{"body_0":"273","body_1":"326","body_2":"279","latch":"323"},"entry":"273"},{"prim":"pre_loop","nodes":{"body_0":"159","body_1":"162","body_2":"168","latch":"185"},"entry":"159"},{"prim":"pre_loop","nodes":{"body_0":"344","body_1":"347","body_2":"353","latch":"371"},"entry":"344"},{"prim":"pre_loop","nodes":{"body_0":"393","body_1":"417","body_2":"399","latch":"414"},"entry":"393"},{"prim":"if","nodes":{"body_0":"67","body_1":"75","cond":"53","follow":"82"},"entry":"53"},{"prim":"if","nodes":{"cond":"41","follow":"86"},"entry":"41"},{"prim":"if","nodes":{"cond":"140","follow":"154"},"entry":"140"},{"prim":"if","nodes":{"cond":"170","follow":"184"},"entry":"170"},{"prim":"if","nodes":{"cond":"188","follow":"194"},"entry":"188"},{"prim":"if","nodes":{"body_0":"291","body_1":"297","body_2":"138","body_3":"168","cond":"279","follow":"323"},"entry":"279"},{"prim":"if","nodes":{"cond":"355","follow":"370"},"entry":"355"},{"prim":"if","nodes":{"cond":"399","follow":"413"},"entry":"399"},{"prim":"if","nodes":{"body_0":"331","body_1":"353","body_2":"374","body_3":"382","cond":"326","follow":"343"},"entry":"326"},{"prim":"if","nodes":{"body_0":"265","cond":"258","follow":"265"},"entry":"258"},{"prim":"if","nodes":{"cond":"250","follow":"256"},"entry":"250"},{"prim":"if","nodes":{"cond":"226","follow":"231"},"entry":"226"},{"prim":"if","nodes":{"body_0":"125","body_1":"195","body_2":"218","cond":"115","follow":"420"},"entry":"115"},{"prim":"if","nodes":{"body_0":"98","body_1":"103","cond":"95","follow":"115"},"entry":"95"},{"prim":"if","nodes":{"cond":"90","follow":"422"},"entry":"90"}]
