[{"prim":"seq","nodes":{"entry":"44","exit":"56"},"entry":"44","exit":"56"},{"prim":"seq","nodes":{"entry":"273","exit":"274"},"entry":"273","exit":"274"},{"prim":"pre_loop","nodes":{"body":"44","cond":"40","exit":"59"},"entry":"40","exit":"59"},{"prim":"seq","nodes":{"entry":"39","exit":"40"},"entry":"39","exit":"40"},{"prim":"if","nodes":{"body":"227","cond":"219","exit":"244"},"entry":"219","exit":"244"},{"prim":"if","nodes":{"body":"215","cond":"209","exit":"218"},"entry":"209","exit":"218"},{"prim":"if","nodes":{"body":"267","cond":"219","exit":"270"},"entry":"219","exit":"270"},{"prim":"if_return","nodes":{"body":"278","cond":"26","exit":"29"},"entry":"26","exit":"29"},{"prim":"if_else","nodes":{"body_false":"205","body_true":"193","cond":"190","exit":"209"},"entry":"190","exit":"209"},{"prim":"if","nodes":{"body":"190","cond":"185","exit":"219"},"entry":"185","exit":"219"},{"prim":"if_else","nodes":{"body_false":"69","body_true":"67","cond":"64","exit":"76"},"entry":"64","exit":"76"},{"prim":"if","nodes":{"body":"64","cond":"39","exit":"79"},"entry":"39","exit":"79"},{"prim":"if_else","nodes":{"body_false":"137","body_true":"106","cond":"100","exit":"153"},"entry":"100","exit":"153"},{"prim":"if_else","nodes":{"body_false":"39","body_true":"80","cond":"26","exit":"86"},"entry":"26","exit":"86"}]
